a007/__init__.py
a007/core.py
a007/presets.py
a007/utils.py
a007-3.0.0.dist-info/METADATA
a007-3.0.0.dist-info/WHEEL
a007-3.0.0.dist-info/entry_points.txt
a007-3.0.0.dist-info/top_level.txt
a007-3.0.0.dist-info/RECORD
