Metadata-Version: 2.4
Name: a007
Version: 3.0.0
Summary: A-007 Pro X Final - Ultra-secure hashing algorithm with customizable entropy-based encoding.
Home-page: https://github.com/yourusername/a007
Author: Arshan Samani
Author-email: your_email@example.com
Keywords: hash,encryption,security,A-007,cryptography,custom hash
Classifier: Programming Language :: Python :: 3
Classifier: License :: OSI Approved :: MIT License
Classifier: Operating System :: OS Independent
Classifier: Topic :: Security :: Cryptography
Classifier: Development Status :: 5 - Production/Stable
Requires-Python: >=3.7
Dynamic: author
Dynamic: author-email
Dynamic: classifier
Dynamic: description
Dynamic: description-content-type
Dynamic: home-page
Dynamic: keywords
Dynamic: requires-python
Dynamic: summary
